dbt/__init__.py
dbt/adapters/__init__.py
dbt/adapters/duckdb/__init__.py
dbt/adapters/duckdb/__version__.py
dbt/adapters/duckdb/cli.py
dbt/adapters/duckdb/column.py
dbt/adapters/duckdb/connections.py
dbt/adapters/duckdb/constants.py
dbt/adapters/duckdb/credentials.py
dbt/adapters/duckdb/impl.py
dbt/adapters/duckdb/relation.py
dbt/adapters/duckdb/secrets.py
dbt/adapters/duckdb/utils.py
dbt/adapters/duckdb/environments/__init__.py
dbt/adapters/duckdb/environments/buenavista.py
dbt/adapters/duckdb/environments/local.py
dbt/adapters/duckdb/environments/motherduck.py
dbt/adapters/duckdb/plugins/__init__.py
dbt/adapters/duckdb/plugins/delta.py
dbt/adapters/duckdb/plugins/excel.py
dbt/adapters/duckdb/plugins/glue.py
dbt/adapters/duckdb/plugins/gsheet.py
dbt/adapters/duckdb/plugins/iceberg.py
dbt/adapters/duckdb/plugins/motherduck.py
dbt/adapters/duckdb/plugins/pd_utils.py
dbt/adapters/duckdb/plugins/postgres.py
dbt/adapters/duckdb/plugins/sqlalchemy.py
dbt/include/__init__.py
dbt/include/duckdb/__init__.py
dbt/include/duckdb/dbt_project.yml
dbt/include/duckdb/sample_profiles.yml
dbt/include/duckdb/macros/adapters.sql
dbt/include/duckdb/macros/catalog.sql
dbt/include/duckdb/macros/columns.sql
dbt/include/duckdb/macros/persist_docs.sql
dbt/include/duckdb/macros/seed.sql
dbt/include/duckdb/macros/snapshot_helper.sql
dbt/include/duckdb/macros/materializations/external.sql
dbt/include/duckdb/macros/materializations/hooks.sql
dbt/include/duckdb/macros/materializations/incremental.sql
dbt/include/duckdb/macros/materializations/table.sql
dbt/include/duckdb/macros/materializations/table_function.sql
dbt/include/duckdb/macros/materializations/incremental_strategy/delete_insert.sql
dbt/include/duckdb/macros/materializations/incremental_strategy/merge.sql
dbt/include/duckdb/macros/materializations/incremental_strategy/merge_config_validation.sql
dbt/include/duckdb/macros/materializations/incremental_strategy/merge_defaults.sql
dbt_duckdb-1.10.0.dist-info/licenses/AUTHORS
dbt_duckdb-1.10.0.dist-info/licenses/LICENSE
dbt_duckdb-1.10.0.dist-info/METADATA
dbt_duckdb-1.10.0.dist-info/WHEEL
dbt_duckdb-1.10.0.dist-info/pbr.json
dbt_duckdb-1.10.0.dist-info/top_level.txt
dbt_duckdb-1.10.0.dist-info/RECORD
