Metadata-Version: 2.4
Name: dbt-duckdb
Version: 1.10.0
Summary: The duckdb adapter plugin for dbt (data build tool)
Home-page: https://github.com/jwills/dbt-duckdb
Author: Josh Wills
Author-email: joshwills+dbt@gmail.com
License: Apache-2
Keywords: setup,distutils
Classifier: Development Status :: 5 - Production/Stable
Classifier: License :: OSI Approved :: Apache Software License
Classifier: Operating System :: Microsoft :: Windows
Classifier: Operating System :: MacOS :: MacOS X
Classifier: Operating System :: POSIX :: Linux
Classifier: Programming Language :: Python :: 3.9
Classifier: Programming Language :: Python :: 3.10
Classifier: Programming Language :: Python :: 3.11
Classifier: Programming Language :: Python :: 3.12
Classifier: Programming Language :: Python :: 3.13
Requires-Python: >=3.9
License-File: LICENSE
Requires-Dist: dbt-common<2,>=1
Requires-Dist: dbt-adapters<2,>=1
Requires-Dist: duckdb>=1.0.0
Requires-Dist: dbt-core>=1.8.0
Provides-Extra: glue
Requires-Dist: boto3; extra == "glue"
Requires-Dist: mypy-boto3-glue; extra == "glue"
Provides-Extra: md
Requires-Dist: duckdb==1.4.1; extra == "md"
Dynamic: author
Dynamic: author-email
Dynamic: classifier
Dynamic: description
Dynamic: keywords
Dynamic: license
Dynamic: license-file
Dynamic: provides-extra
Dynamic: summary
